access_moppy/__init__.py
access_moppy/_config.py
access_moppy/_version.py
access_moppy/atmosphere.py
access_moppy/base.py
access_moppy/batch_cmoriser.py
access_moppy/defaults.py
access_moppy/driver.py
access_moppy/ocean.py
access_moppy/ocean_supergrid.py
access_moppy/tracking.py
access_moppy/utilities.py
access_moppy/vocabulary_processors.py
access_moppy/dashboard/__init__.py
access_moppy/dashboard/cmor_dashboard.py
access_moppy/derivations/__init__.py
access_moppy/derivations/calc_atmos.py
access_moppy/derivations/calc_land.py
access_moppy/derivations/calc_utils.py
access_moppy/examples/batch_config.yml
access_moppy/examples/show_config.py
access_moppy/executors/pbs_scheduler.py
access_moppy/mappings/ACCESS-ESM1.6_mappings.json
access_moppy/mappings/ACCESS-OM3_mappings.json
access_moppy/vocabularies/cmip6_cmor_tables/LICENSE.md
access_moppy/vocabularies/cmip6_cmor_tables/README.md
access_moppy/vocabularies/cmip6_cmor_tables/CMIP6_CVs/CITATION.cff
access_moppy/vocabularies/cmip6_cmor_tables/CMIP6_CVs/CMIP6_DRS.json
access_moppy/vocabularies/cmip6_cmor_tables/CMIP6_CVs/CMIP6_activity_id.json
access_moppy/vocabularies/cmip6_cmor_tables/CMIP6_CVs/CMIP6_experiment_id.json
access_moppy/vocabularies/cmip6_cmor_tables/CMIP6_CVs/CMIP6_frequency.json
access_moppy/vocabularies/cmip6_cmor_tables/CMIP6_CVs/CMIP6_grid_label.json
access_moppy/vocabularies/cmip6_cmor_tables/CMIP6_CVs/CMIP6_institution_id.json
access_moppy/vocabularies/cmip6_cmor_tables/CMIP6_CVs/CMIP6_license.json
access_moppy/vocabularies/cmip6_cmor_tables/CMIP6_CVs/CMIP6_nominal_resolution.json
access_moppy/vocabularies/cmip6_cmor_tables/CMIP6_CVs/CMIP6_realm.json
access_moppy/vocabularies/cmip6_cmor_tables/CMIP6_CVs/CMIP6_required_global_attributes.json
access_moppy/vocabularies/cmip6_cmor_tables/CMIP6_CVs/CMIP6_source_id.json
access_moppy/vocabularies/cmip6_cmor_tables/CMIP6_CVs/CMIP6_source_type.json
access_moppy/vocabularies/cmip6_cmor_tables/CMIP6_CVs/CMIP6_sub_experiment_id.json
access_moppy-1.0.2a1.dist-info/licenses/LICENCE.txt
access_moppy-1.0.2a1.dist-info/METADATA
access_moppy-1.0.2a1.dist-info/WHEEL
access_moppy-1.0.2a1.dist-info/entry_points.txt
access_moppy-1.0.2a1.dist-info/top_level.txt
access_moppy-1.0.2a1.dist-info/RECORD
