Metadata-Version: 2.4
Name: access_moppy
Version: 1.0.2a1
Summary: ACCESS Model Output Post-Processor, maps raw model output to CMIP-style defined variables and produce post-processed output using CMOR3
Author-email: Romain Beucher <romain.beucher@anu.edu.au>
License: Apache-2.0
Keywords: ACCESS,post-processing
Classifier: Development Status :: 3 - Alpha
Classifier: Intended Audience :: Science/Research
Classifier: License :: OSI Approved :: Apache Software License
Classifier: Operating System :: OS Independent
Classifier: Programming Language :: Python :: 3.11
Classifier: Programming Language :: Python :: 3.12
Classifier: Programming Language :: Python :: 3.13
Requires-Python: >=3.11
License-File: LICENCE.txt
Requires-Dist: numpy
Requires-Dist: pandas
Requires-Dist: xarray
Requires-Dist: netCDF4
Requires-Dist: cftime
Requires-Dist: dask
Requires-Dist: distributed>=2024.0.0
Requires-Dist: pyyaml
Requires-Dist: tqdm
Requires-Dist: requests
Requires-Dist: parsl
Requires-Dist: jinja2
Provides-Extra: dashboard
Requires-Dist: streamlit>=1.35.0; extra == "dashboard"
Provides-Extra: test
Requires-Dist: pytest; extra == "test"
Requires-Dist: pytest-cov; extra == "test"
Requires-Dist: pytest-subtests; extra == "test"
Requires-Dist: ruff; extra == "test"
Provides-Extra: docs
Requires-Dist: sphinx>=7.0.0; extra == "docs"
Requires-Dist: sphinx-rtd-theme>=1.3.0; extra == "docs"
Requires-Dist: sphinx-autodoc-typehints>=1.23.0; extra == "docs"
Requires-Dist: myst-parser>=2.0.0; extra == "docs"
Requires-Dist: sphinx-autoapi>=3.0.0; extra == "docs"
Requires-Dist: nbsphinx>=0.9.0; extra == "docs"
Requires-Dist: ipython>=8.0.0; extra == "docs"
Requires-Dist: pygments>=2.15.0; extra == "docs"
Dynamic: license-file
